MANIFEST.in
README.txt
setup.py
collective/__init__.py
collective.jqueryui.egg-info/PKG-INFO
collective.jqueryui.egg-info/SOURCES.txt
collective.jqueryui.egg-info/dependency_links.txt
collective.jqueryui.egg-info/entry_points.txt
collective.jqueryui.egg-info/namespace_packages.txt
collective.jqueryui.egg-info/not-zip-safe
collective.jqueryui.egg-info/requires.txt
collective.jqueryui.egg-info/top_level.txt
collective/jqueryui/__init__.py
collective/jqueryui/configure.zcml
collective/jqueryui/patch.py
collective/jqueryui/tests.py
collective/jqueryui/jquery.ui/AUTHORS.txt
collective/jqueryui/jquery.ui/GPL-LICENSE.txt
collective/jqueryui/jquery.ui/MIT-LICENSE.txt
collective/jqueryui/jquery.ui/jquery-1.3.js
collective/jqueryui/jquery.ui/version.txt
collective/jqueryui/jquery.ui/demos/demos.css
collective/jqueryui/jquery.ui/demos/index.html
collective/jqueryui/jquery.ui/demos/ui.theme.css
collective/jqueryui/jquery.ui/demos/accordion/collapsible.html
collective/jqueryui/jquery.ui/demos/accordion/custom_icons.html
collective/jqueryui/jquery.ui/demos/accordion/default.html
collective/jqueryui/jquery.ui/demos/accordion/fillspace.html
collective/jqueryui/jquery.ui/demos/accordion/index.html
collective/jqueryui/jquery.ui/demos/accordion/mouseover.html
collective/jqueryui/jquery.ui/demos/datepicker/alt_field.html
collective/jqueryui/jquery.ui/demos/datepicker/buttonbar.html
collective/jqueryui/jquery.ui/demos/datepicker/date_formats.html
collective/jqueryui/jquery.ui/demos/datepicker/default.html
collective/jqueryui/jquery.ui/demos/datepicker/dropdown_month_year.html
collective/jqueryui/jquery.ui/demos/datepicker/icon_trigger.html
collective/jqueryui/jquery.ui/demos/datepicker/index.html
collective/jqueryui/jquery.ui/demos/datepicker/inline.html
collective/jqueryui/jquery.ui/demos/datepicker/localization.html
collective/jqueryui/jquery.ui/demos/datepicker/min_max.html
collective/jqueryui/jquery.ui/demos/datepicker/multiple_calendars.html
collective/jqueryui/jquery.ui/demos/datepicker/images/calendar.gif
collective/jqueryui/jquery.ui/demos/dialog/default.html
collective/jqueryui/jquery.ui/demos/dialog/index.html
collective/jqueryui/jquery.ui/demos/dialog/modal.html
collective/jqueryui/jquery.ui/demos/dialog/modal_confirmation.html
collective/jqueryui/jquery.ui/demos/dialog/modal_form.html
