Metadata-Version: 1.0
Name: collective.jqueryui
Version: 1.6rc5
Summary: UNKNOWN
Home-page: http://
Author: Rok Garbas and contributors
Author-email: rok.garbas@gmail.com
License: MIT
Keywords: plone jquery jqueryui
Platform: UNKNOWN
Classifier: Framework :: Plone
Classifier: Programming Language :: Python
Classifier: Topic :: Software Development :: Libraries :: Python Modules
